distribution_algebra/__init__.py
distribution_algebra/__main__.py
distribution_algebra/algebra.py
distribution_algebra/beta.py
distribution_algebra/beta4.py
distribution_algebra/binomial.py
distribution_algebra/config.py
distribution_algebra/distribution.py
distribution_algebra/examples/beta_slider.py
distribution_algebra/lognormal.py
distribution_algebra/normal.py
distribution_algebra/plotting.py
distribution_algebra/poisson.py
distribution_algebra/py.typed
tests/__init__.py
tests/conftest.py
tests/test_algebra.py
tests/test_lognormal.py
tests/test_normal.py
distribution_algebra-0.1.26.dist-info/LICENSE
distribution_algebra-0.1.26.dist-info/METADATA
distribution_algebra-0.1.26.dist-info/WHEEL
distribution_algebra-0.1.26.dist-info/RECORD
