Metadata-Version: 2.1
Name: distribution-algebra
Version: 0.1.26
Summary: A python package that implements an easy-to-use interface for random variables, statistical distributions, and their algebra.
Home-page: https://vaibhavkarve.github.io/distribution-algebra/
License: GPL-3.0-or-later
Keywords: statistics,typed,python3,distribution,random,algebra
Author: Vaibhav Karve
Author-email: vkarve@protonmail.com
Requires-Python: >=3.9,<3.12
Classifier: Development Status :: 4 - Beta
Classifier: Intended Audience :: Science/Research
Classifier: License :: OSI Approved :: GNU General Public License v3 or later (GPLv3+)
Classifier: Natural Language :: English
Classifier: Operating System :: OS Independent
Classifier: Programming Language :: Python :: 3
Classifier: Programming Language :: Python :: 3.9
Classifier: Programming Language :: Python :: 3.10
Classifier: Programming Language :: Python :: 3.11
Classifier: Topic :: Scientific/Engineering :: Mathematics
Classifier: Typing :: Typed
Requires-Dist: attrs (>=22.2.0,<23.0.0)
Requires-Dist: loguru (>=0.6.0,<0.7.0)
Requires-Dist: matplotlib (>=3.6.2,<4.0.0)
Requires-Dist: multipledispatch (>=0.6.0,<0.7.0)
Requires-Dist: mypy (>=1.3.0)
Requires-Dist: numpy (>=1.24.0,<2.0.0)
Requires-Dist: scipy (>=1.9.3,<2.0.0)
Requires-Dist: wheel (>=0.38.1)
Project-URL: Documentation, https://vaibhavkarve.github.io/distribution-algebra/
Project-URL: Repository, https://github.com/vaibhavkarve/distribution-algebra
